vendoring/__init__.py
vendoring/__main__.py
vendoring/cli.py
vendoring/configuration.py
vendoring/errors.py
vendoring/ui.py
vendoring/utils.py
vendoring/tasks/__init__.py
vendoring/tasks/cleanup.py
vendoring/tasks/license.py
vendoring/tasks/stubs.py
vendoring/tasks/update.py
vendoring/tasks/vendor.py
vendoring-1.2.0.dist-info/entry_points.txt
vendoring-1.2.0.dist-info/LICENSE
vendoring-1.2.0.dist-info/WHEEL
vendoring-1.2.0.dist-info/METADATA
vendoring-1.2.0.dist-info/RECORD
