Metadata-Version: 2.1
Name: vendoring
Version: 1.2.0
Summary: A command line tool, to simplify vendoring pure Python dependencies.
Author-email: Pradyun Gedam <pradyunsg@gmail.com>
Requires-Python: ~= 3.8
Classifier: Intended Audience :: Developers
Classifier: License :: OSI Approved :: MIT License
Classifier: Programming Language :: Python :: 3
Classifier: Topic :: Software Development :: Libraries :: Python Modules
Requires-Dist: click
Requires-Dist: rich
Requires-Dist: jsonschema
Requires-Dist: toml
Requires-Dist: requests
Requires-Dist: packaging
Requires-Dist: sphinx ; extra == "doc"
Requires-Dist: pytest ; extra == "test"
Requires-Dist: pytest-cov ; extra == "test"
Requires-Dist: pytest-mock ; extra == "test"
Project-URL: Source, https://github.com/pradyunsg/vendoring
Provides-Extra: doc
Provides-Extra: test
